safe/__init__.py
safe/safe.py
save_deep/__init__.py
save_deep/save_deep.py
django_save_deep-0.0.2.dist-info/LICENSE
django_save_deep-0.0.2.dist-info/METADATA
django_save_deep-0.0.2.dist-info/WHEEL
django_save_deep-0.0.2.dist-info/top_level.txt
django_save_deep-0.0.2.dist-info/RECORD
