Metadata-Version: 2.1
Name: django-save-deep
Version: 0.0.2
Summary: Safes a complete tree of django models - from bottom to top.
Home-page: https://github.com/tom-010/django-save-deep
Author: Thomas Deniffel
Author-email: tdeniffel@gmail.com
License: Apache2
Platform: UNKNOWN
Classifier: Development Status :: 4 - Beta
Classifier: Intended Audience :: Developers
Classifier: Programming Language :: Python
Classifier: Programming Language :: Python :: 3 :: Only
Classifier: Programming Language :: Python :: 3.6
Classifier: Programming Language :: Python :: 3.7
Requires-Python: >=3
License-File: LICENSE
Requires-Dist: Django (>=3.0.0)
